zmq_ai_client_python/__init__.py
zmq_ai_client_python/async_client.py
zmq_ai_client_python/base_client.py
zmq_ai_client_python/client.py
zmq_ai_client_python/error.py
zmq_ai_client_python/schema/__init__.py
zmq_ai_client_python/schema/base.py
zmq_ai_client_python/schema/completion.py
zmq_ai_client_python/schema/health_check.py
zmq_ai_client_python/schema/session_state.py
zmq_ai_client_python/schema/zmq_message_header.py
zmq_ai_client_python/tests/__init__.py
zmq_ai_client_python/tests/async_client_load_tests.py
zmq_ai_client_python/tests/async_client_tests.py
zmq_ai_client_python/tests/client_load_tests.py
zmq_ai_client_python/tests/client_parallel_load_test.py
zmq_ai_client_python/tests/client_tests.py
zmq_ai_client_python/tests/msgpack_tests.py
zmq_ai_client_python/tests/zmq_message_test.py
zmq_ai_client_python-1.2.8.dist-info/METADATA
zmq_ai_client_python-1.2.8.dist-info/WHEEL
zmq_ai_client_python-1.2.8.dist-info/top_level.txt
zmq_ai_client_python-1.2.8.dist-info/RECORD
